{
    "ml": [],
    "cl": [
        [
            99,
            297
        ],
        [
            183,
            276
        ],
        [
            24,
            239
        ],
        [
            109,
            257
        ],
        [
            113,
            308
        ],
        [
            147,
            248
        ],
        [
            108,
            168
        ],
        [
            36,
            224
        ],
        [
            227,
            275
        ],
        [
            98,
            187
        ],
        [
            166,
            241
        ],
        [
            122,
            326
        ],
        [
            220,
            239
        ],
        [
            108,
            155
        ],
        [
            56,
            333
        ],
        [
            168,
            319
        ],
        [
            136,
            202
        ],
        [
            117,
            194
        ],
        [
            39,
            216
        ],
        [
            3,
            237
        ],
        [
            110,
            273
        ],
        [
            48,
            176
        ],
        [
            11,
            189
        ],
        [
            4,
            184
        ],
        [
            134,
            288
        ],
        [
            92,
            221
        ],
        [
            77,
            207
        ],
        [
            185,
            334
        ],
        [
            243,
            291
        ],
        [
            85,
            255
        ],
        [
            159,
            261
        ],
        [
            92,
            271
        ],
        [
            177,
            294
        ],
        [
            226,
            273
        ],
        [
            60,
            312
        ],
        [
            235,
            309
        ],
        [
            71,
            326
        ],
        [
            228,
            280
        ],
        [
            76,
            159
        ],
        [
            179,
            237
        ],
        [
            142,
            167
        ],
        [
            46,
            143
        ],
        [
            104,
            238
        ],
        [
            57,
            217
        ],
        [
            163,
            268
        ],
        [
            143,
            334
        ],
        [
            7,
            324
        ],
        [
            202,
            313
        ],
        [
            234,
            335
        ],
        [
            22,
            291
        ],
        [
            122,
            172
        ],
        [
            139,
            241
        ],
        [
            100,
            282
        ],
        [
            274,
            303
        ],
        [
            205,
            326
        ],
        [
            33,
            264
        ],
        [
            62,
            175
        ],
        [
            12,
            189
        ],
        [
            103,
            229
        ],
        [
            186,
            262
        ],
        [
            281,
            320
        ],
        [
            234,
            279
        ],
        [
            162,
            284
        ],
        [
            104,
            222
        ],
        [
            152,
            232
        ],
        [
            25,
            296
        ],
        [
            175,
            224
        ],
        [
            26,
            224
        ],
        [
            137,
            283
        ],
        [
            238,
            316
        ],
        [
            210,
            231
        ],
        [
            140,
            315
        ],
        [
            73,
            249
        ],
        [
            31,
            325
        ],
        [
            230,
            319
        ],
        [
            173,
            266
        ],
        [
            213,
            240
        ],
        [
            110,
            182
        ],
        [
            272,
            329
        ],
        [
            98,
            333
        ],
        [
            98,
            300
        ],
        [
            70,
            229
        ],
        [
            270,
            303
        ],
        [
            6,
            170
        ],
        [
            65,
            260
        ],
        [
            246,
            295
        ],
        [
            229,
            313
        ],
        [
            46,
            308
        ],
        [
            140,
            206
        ],
        [
            59,
            147
        ],
        [
            31,
            271
        ],
        [
            49,
            152
        ],
        [
            120,
            147
        ],
        [
            84,
            198
        ],
        [
            77,
            194
        ],
        [
            170,
            324
        ],
        [
            123,
            240
        ],
        [
            77,
            208
        ],
        [
            84,
            306
        ],
        [
            99,
            249
        ]
    ],
    "sml": [],
    "scl": [],
    "sml_proba": [],
    "scl_proba": []
}